orc/__init__.py
orc-0.1.0.dist-info/LICENSE
orc-0.1.0.dist-info/METADATA
orc-0.1.0.dist-info/WHEEL
orc-0.1.0.dist-info/top_level.txt
orc-0.1.0.dist-info/RECORD
